deforestation/__init__.py
deforestation/cli.py
deforestation/infer.py
deforestation/io.py
deforestation_detection-0.1.2.dist-info/METADATA
deforestation_detection-0.1.2.dist-info/WHEEL
deforestation_detection-0.1.2.dist-info/entry_points.txt
deforestation_detection-0.1.2.dist-info/licenses/LICENSE
deforestation_detection-0.1.2.dist-info/RECORD
