Metadata-Version: 2.4
Name: deforestation-detection
Version: 0.1.2
Summary: Deforestation segmentation from Sentinel tiles using a U-Net exported to ONNX.
Author: Arnav Kumar
License: MIT License
License-File: LICENSE
Keywords: deforestation,onnx,remote-sensing,segmentation,sentinel
Requires-Python: >=3.11
Requires-Dist: numpy>=1.26
Requires-Dist: onnxruntime>=1.17.0
Requires-Dist: pillow>=10.0
Requires-Dist: rasterio>=1.3.10
Provides-Extra: dev
Requires-Dist: build>=1.2; extra == 'dev'
Requires-Dist: pytest>=8.0; extra == 'dev'
Requires-Dist: ruff>=0.6; extra == 'dev'
Requires-Dist: twine>=5.0; extra == 'dev'
Provides-Extra: gpu
Requires-Dist: onnxruntime-gpu>=1.17.0; extra == 'gpu'
